nirahmq/__init__.py
nirahmq/device.py
nirahmq/enums.py
nirahmq/mqtt.py
nirahmq/utils.py
nirahmq/components/__init__.py
nirahmq/components/base.py
nirahmq/components/components.py
nirahmq-0.1.3a0.dist-info/METADATA
nirahmq-0.1.3a0.dist-info/WHEEL
nirahmq-0.1.3a0.dist-info/licenses/LICENSE
nirahmq-0.1.3a0.dist-info/RECORD
