Metadata-Version: 2.4
Name: nirahmq
Version: 0.1.3a0
Summary: A Home Assistant MQTT client library
Project-URL: Homepage, https://github.com/dionisis2014/nirahmq
Project-URL: Source, https://github.com/dionisis2014/nirahmq
Project-URL: Download, https://github.com/dionisis2014/nirahmq/releases
Project-URL: Documentation, https://dionisis2014.github.io/nirahmq/master/
Project-URL: Issues, https://github.com/dionisis2014/nirahmq/issues
Author-email: Dionisis Toulatos <toulatosdionisis@gmail.com>
Maintainer-email: Dionisis Toulatos <toulatosdionisis@gmail.com>
License-Expression: AGPL-3.0-or-later
License-File: LICENSE
Keywords: home assistant,mqtt,mqtt client,mqtt discovery
Classifier: Development Status :: 3 - Alpha
Classifier: Framework :: Pydantic
Classifier: Intended Audience :: Developers
Classifier: License :: OSI Approved :: GNU Affero General Public License v3 or later (AGPLv3+)
Classifier: Natural Language :: English
Classifier: Operating System :: MacOS :: MacOS X
Classifier: Operating System :: Microsoft :: Windows
Classifier: Operating System :: POSIX
Classifier: Programming Language :: Python
Classifier: Programming Language :: Python :: 3.12
Classifier: Programming Language :: Python :: 3.13
Classifier: Topic :: Communications
Classifier: Topic :: Home Automation
Classifier: Topic :: Software Development :: Libraries
Classifier: Topic :: Software Development :: Libraries :: Python Modules
Requires-Python: >=3.12
Requires-Dist: paho-mqtt
Requires-Dist: pydantic
Provides-Extra: dev
Requires-Dist: interrogate; extra == 'dev'
Requires-Dist: pylint; extra == 'dev'
Provides-Extra: docs
Requires-Dist: furo; extra == 'docs'
Requires-Dist: sphinx; extra == 'docs'
Requires-Dist: sphinx-copybutton; extra == 'docs'
Requires-Dist: sphinx-multiversion; extra == 'docs'
